<?xml version="1.0" encoding="utf-8" standalone="yes"?>
<post>
  <author>Admin</author>
  <title>one more carousel</title>
  <description>ascsdf sdfs dfsdf[CAROUSEL:newAl]</description>
  <content>&lt;p&gt;ascsdf sdf&lt;/p&gt;&lt;p&gt;s d&lt;/p&gt;&lt;p&gt;fsd&lt;/p&gt;&lt;p&gt;f&lt;/p&gt;&lt;p&gt;&lt;span style="color: rgb(58, 135, 173); font-family: 'Times New Roman'; font-size: medium; line-height: normal; background-color: rgb(217, 237, 247);"&gt;[CAROUSEL:&lt;/span&gt;&lt;span style="color: rgb(58, 135, 173); font-family: 'Times New Roman'; font-size: medium; line-height: normal; background-color: rgb(217, 237, 247);"&gt;df&lt;/span&gt;&lt;span style="color: rgb(58, 135, 173); font-family: 'Times New Roman'; font-size: medium; line-height: normal; background-color: rgb(217, 237, 247);"&gt;]&lt;/span&gt;&lt;/p&gt;&lt;p&gt;&lt;span style="color: rgb(58, 135, 173); font-family: 'Times New Roman'; font-size: medium; line-height: normal; background-color: rgb(217, 237, 247);"&gt;&lt;br&gt;&lt;/span&gt;&lt;/p&gt;&lt;p&gt;&lt;span style="color: rgb(58, 135, 173); font-family: 'Times New Roman'; font-size: medium; line-height: normal; background-color: rgb(217, 237, 247);"&gt;&lt;br&gt;&lt;/span&gt;&lt;/p&gt;&lt;p&gt;&lt;span style="color: rgb(58, 135, 173); font-family: 'Times New Roman'; font-size: medium; line-height: normal; background-color: rgb(217, 237, 247);"&gt;&lt;br&gt;&lt;/span&gt;&lt;/p&gt;&lt;img src="/image.axd?picture=%2f2014%2f09%2fMens-Shirts-Beautifull-Colletion-2014-by-Fortune-Vogue-1.jpg" style="width: 106.5px; height: 79.875px;"&gt;</content>
  <ispublished>True</ispublished>
  <isdeleted>True</isdeleted>
  <iscommentsenabled>True</iscommentsenabled>
  <pubDate>2014-09-03 17:28:00</pubDate>
  <lastModified>2014-09-03 17:31:04</lastModified>
  <raters>0</raters>
  <rating>0</rating>
  <slug>one-more-carousel</slug>
  <tags />
  <comments />
  <categories />
  <notifications />
</post>